<?xml version="1.0" encoding="utf-8" ?>
<response>
  <status>
    <code>0</code>
  </status>
  <wc:info xmlns:wc="urn:com.microsoft.wc.methods.response.GetThings3">
    <group>
      <thing>
        <thing-id version-stamp="c3b0413d-9e69-40c7-bbb4-e3ebf9a7ecc3">0954ad63-ac67-4ae0-8592-259bd82ac369</thing-id>
        <type-id name="Blood pressure">ca3c57f4-f4c1-4e15-be67-0a3caf5414ed</type-id>
        <thing-state>Active</thing-state>
        <flags>0</flags>
        <eff-date>2017-03-14T17:56:25</eff-date>
        <created>
          <timestamp>2017-03-15T00:56:26.243Z</timestamp>
          <app-id name="Test Source">58d02387-f5c2-44b7-b0c6-f1baa85d9784</app-id>
          <person-id name="Test User">2d44d876-3bde-482b-a2af-ba133bc41fa9</person-id>
          <access-avenue>Offline</access-avenue>
          <audit-action>Created</audit-action>
          <master-app-id>d6318dff-5352-4a10-a140-6c82c6536a3b</master-app-id>
        </created>
        <updated>
          <timestamp>2017-03-15T00:56:26.243Z</timestamp>
          <app-id name="Test Source">58d02387-f5c2-44b7-b0c6-f1baa85d9784</app-id>
          <person-id name="Test User">2d44d876-3bde-482b-a2af-ba133bc41fa9</person-id>
          <access-avenue>Offline</access-avenue>
          <audit-action>Created</audit-action>
          <master-app-id>d6318dff-5352-4a10-a140-6c82c6536a3b</master-app-id>
        </updated>
        <data-xml>
          <blood-pressure>
            <when>
              <date>
                <y>2017</y>
                <m>3</m>
                <d>14</d>
              </date>
              <time>
                <h>17</h>
                <m>56</m>
                <s>25</s>
                <f>0</f>
              </time>
            </when>
            <systolic>101</systolic>
            <diastolic>99</diastolic>
            <pulse>123</pulse>
          </blood-pressure>
          <common />
        </data-xml>
        <eff-permissions immutable="false">
          <permission>Read</permission>
          <permission>Update</permission>
          <permission>Create</permission>
          <permission>Delete</permission>
        </eff-permissions>
      </thing>
      <thing>
        <thing-id version-stamp="e9c6356f-173b-4dae-87a4-55e9885e1934">954a2cf4-c4b2-4488-ae0e-f06c975d4649</thing-id>
        <type-id name="Blood pressure">ca3c57f4-f4c1-4e15-be67-0a3caf5414ed</type-id>
        <thing-state>Active</thing-state>
        <flags>0</flags>
        <eff-date>2017-02-10T11:45:36</eff-date>
        <created>
          <timestamp>2017-02-10T19:45:36.963Z</timestamp>
          <app-id name="Test Source">72704e7a-0c9a-4c21-9094-33562c8327d5</app-id>
          <person-id name="Test User">2d44d876-3bde-482b-a2af-ba133bc41fa9</person-id>
          <access-avenue>Offline</access-avenue>
          <audit-action>Created</audit-action>
          <master-app-id>d6318dff-5352-4a10-a140-6c82c6536a3b</master-app-id>
        </created>
        <updated>
          <timestamp>2017-02-10T19:45:36.963Z</timestamp>
          <app-id name="Test Source">72704e7a-0c9a-4c21-9094-33562c8327d5</app-id>
          <person-id name="Test User">2d44d876-3bde-482b-a2af-ba133bc41fa9</person-id>
          <access-avenue>Offline</access-avenue>
          <audit-action>Created</audit-action>
          <master-app-id>d6318dff-5352-4a10-a140-6c82c6536a3b</master-app-id>
        </updated>
        <data-xml>
          <blood-pressure>
            <when>
              <date>
                <y>2017</y>
                <m>2</m>
                <d>10</d>
              </date>
              <time>
                <h>11</h>
                <m>45</m>
                <s>36</s>
                <f>0</f>
              </time>
            </when>
            <systolic>101</systolic>
            <diastolic>85</diastolic>
            <pulse>900</pulse>
          </blood-pressure>
          <common />
        </data-xml>
        <eff-permissions immutable="false">
          <permission>Read</permission>
          <permission>Update</permission>
          <permission>Create</permission>
          <permission>Delete</permission>
        </eff-permissions>
      </thing>
      <thing>
        <thing-id version-stamp="ffebce79-0710-43e9-86ec-a1ed34aaf7bc">593a06e7-97ac-45f2-84c9-e04ed97a6a0d</thing-id>
        <type-id name="Contact">25c94a9f-9d3d-4576-96dc-6791178a8143</type-id>
        <thing-state>Active</thing-state>
        <flags>0</flags>
        <eff-date>2017-02-08T23:24:18.401</eff-date>
        <created>
          <timestamp>2017-02-08T23:24:18.243Z</timestamp>
          <app-id name="Test Source">df8399dc-d3f7-4645-bf4a-31989f3464b3</app-id>
          <person-id name="Test User">2d44d876-3bde-482b-a2af-ba133bc41fa9</person-id>
          <access-avenue>Offline</access-avenue>
          <audit-action>Created</audit-action>
          <master-app-id>30325d89-0308-4744-843f-c88599db77c7</master-app-id>
        </created>
        <updated>
          <timestamp>2017-02-08T23:24:18.243Z</timestamp>
          <app-id name="Test Source">df8399dc-d3f7-4645-bf4a-31989f3464b3</app-id>
          <person-id name="Test User">2d44d876-3bde-482b-a2af-ba133bc41fa9</person-id>
          <access-avenue>Offline</access-avenue>
          <audit-action>Created</audit-action>
          <master-app-id>30325d89-0308-4744-843f-c88599db77c7</master-app-id>
        </updated>
        <data-xml>
          <person>
            <name>
              <full>Dr. Come O. fhqwhgads</full>
              <title>
                <text>Dr.</text>
                <code>
                  <value>Dr</value>
                  <type>name-prefixes</type>
                </code>
              </title>
              <first>Come</first>
              <middle>On</middle>
              <last>fhqwhgads</last>
              <suffix>
                <text />
              </suffix>
            </name>
            <contact />
            <type>
              <text />
            </type>
          </person>
          <common>
            <note />
          </common>
        </data-xml>
        <eff-permissions immutable="false">
          <permission>Read</permission>
          <permission>Update</permission>
          <permission>Create</permission>
          <permission>Delete</permission>
        </eff-permissions>
      </thing>
      <thing>
        <thing-id version-stamp="1d242776-6da8-472d-8f98-4ad13f822cb5">a95f0986-2b3a-4563-9ff9-696a5a7b8129</thing-id>
        <type-id name="Blood pressure">ca3c57f4-f4c1-4e15-be67-0a3caf5414ed</type-id>
        <thing-state>Active</thing-state>
        <flags>0</flags>
        <eff-date>2017-02-08T15:58:27</eff-date>
        <created>
          <timestamp>2017-02-08T23:58:27.507Z</timestamp>
          <app-id name="Test Source">ab9d8982-ae10-4cb2-b7da-865c07775fcb</app-id>
          <person-id name="Test User">2d44d876-3bde-482b-a2af-ba133bc41fa9</person-id>
          <access-avenue>Offline</access-avenue>
          <audit-action>Created</audit-action>
          <master-app-id>30325d89-0308-4744-843f-c88599db77c7</master-app-id>
        </created>
        <updated>
          <timestamp>2017-02-08T23:58:27.507Z</timestamp>
          <app-id name="Test Source">ab9d8982-ae10-4cb2-b7da-865c07775fcb</app-id>
          <person-id name="Test User">2d44d876-3bde-482b-a2af-ba133bc41fa9</person-id>
          <access-avenue>Offline</access-avenue>
          <audit-action>Created</audit-action>
          <master-app-id>30325d89-0308-4744-843f-c88599db77c7</master-app-id>
        </updated>
        <data-xml>
          <blood-pressure>
            <when>
              <date>
                <y>2017</y>
                <m>2</m>
                <d>8</d>
              </date>
              <time>
                <h>15</h>
                <m>58</m>
                <s>27</s>
                <f>0</f>
              </time>
            </when>
            <systolic>100</systolic>
            <diastolic>85</diastolic>
            <pulse>900</pulse>
          </blood-pressure>
          <common />
        </data-xml>
        <eff-permissions immutable="false">
          <permission>Read</permission>
          <permission>Update</permission>
          <permission>Create</permission>
          <permission>Delete</permission>
        </eff-permissions>
      </thing>
      <thing>
        <thing-id version-stamp="f1a3c6f7-abcf-497f-8759-169e17978b89">eebfe544-2239-44a3-9ca7-116fd2780b43</thing-id>
        <type-id name="Blood pressure">ca3c57f4-f4c1-4e15-be67-0a3caf5414ed</type-id>
        <thing-state>Active</thing-state>
        <flags>0</flags>
        <eff-date>2017-02-08T15:30:16</eff-date>
        <created>
          <timestamp>2017-02-08T23:30:16.67Z</timestamp>
          <app-id name="Test Source">b5cb7d2e-be2c-4c61-b09e-ed67da4a9e69</app-id>
          <person-id name="Test User">2d44d876-3bde-482b-a2af-ba133bc41fa9</person-id>
          <access-avenue>Offline</access-avenue>
          <audit-action>Created</audit-action>
          <master-app-id>30325d89-0308-4744-843f-c88599db77c7</master-app-id>
        </created>
        <updated>
          <timestamp>2017-02-08T23:30:16.67Z</timestamp>
          <app-id name="Test Source">b5cb7d2e-be2c-4c61-b09e-ed67da4a9e69</app-id>
          <person-id name="Test User">2d44d876-3bde-482b-a2af-ba133bc41fa9</person-id>
          <access-avenue>Offline</access-avenue>
          <audit-action>Created</audit-action>
          <master-app-id>30325d89-0308-4744-843f-c88599db77c7</master-app-id>
        </updated>
        <data-xml>
          <blood-pressure>
            <when>
              <date>
                <y>2017</y>
                <m>2</m>
                <d>8</d>
              </date>
              <time>
                <h>15</h>
                <m>30</m>
                <s>16</s>
                <f>0</f>
              </time>
            </when>
            <systolic>120</systolic>
            <diastolic>85</diastolic>
            <pulse>900</pulse>
          </blood-pressure>
          <common />
        </data-xml>
        <eff-permissions immutable="false">
          <permission>Read</permission>
          <permission>Update</permission>
          <permission>Create</permission>
          <permission>Delete</permission>
        </eff-permissions>
      </thing>
      <thing>
        <thing-id version-stamp="cfdb1b57-03ef-4d33-91bc-a3b53bfc4c50">752c58e9-ae16-46d3-aa5e-0f21ce507ae7</thing-id>
        <type-id name="Blood pressure">ca3c57f4-f4c1-4e15-be67-0a3caf5414ed</type-id>
        <thing-state>Active</thing-state>
        <flags>0</flags>
        <eff-date>2017-02-08T15:21:57</eff-date>
        <created>
          <timestamp>2017-02-08T23:21:56.953Z</timestamp>
          <app-id name="Test Source">df8399dc-d3f7-4645-bf4a-31989f3464b3</app-id>
          <person-id name="Test User">2d44d876-3bde-482b-a2af-ba133bc41fa9</person-id>
          <access-avenue>Offline</access-avenue>
          <audit-action>Created</audit-action>
          <master-app-id>30325d89-0308-4744-843f-c88599db77c7</master-app-id>
        </created>
        <updated>
          <timestamp>2017-02-08T23:21:56.953Z</timestamp>
          <app-id name="Test Source">df8399dc-d3f7-4645-bf4a-31989f3464b3</app-id>
          <person-id name="Test User">2d44d876-3bde-482b-a2af-ba133bc41fa9</person-id>
          <access-avenue>Offline</access-avenue>
          <audit-action>Created</audit-action>
          <master-app-id>30325d89-0308-4744-843f-c88599db77c7</master-app-id>
        </updated>
        <data-xml>
          <blood-pressure>
            <when>
              <date>
                <y>2017</y>
                <m>2</m>
                <d>8</d>
              </date>
              <time>
                <h>15</h>
                <m>21</m>
                <s>57</s>
                <f>0</f>
              </time>
            </when>
            <systolic>100</systolic>
            <diastolic>90</diastolic>
            <pulse>80</pulse>
          </blood-pressure>
          <common />
        </data-xml>
        <eff-permissions immutable="false">
          <permission>Read</permission>
          <permission>Update</permission>
          <permission>Create</permission>
          <permission>Delete</permission>
        </eff-permissions>
      </thing>
      <thing>
        <thing-id version-stamp="83c2b710-2185-4ed7-a9f2-6ffeacde0b57">7f602506-29ac-46be-91c1-ccb751413722</thing-id>
        <type-id name="Blood pressure">ca3c57f4-f4c1-4e15-be67-0a3caf5414ed</type-id>
        <thing-state>Active</thing-state>
        <flags>0</flags>
        <eff-date>2017-02-08T15:00:57</eff-date>
        <created>
          <timestamp>2017-02-08T23:01:03.543Z</timestamp>
          <app-id name="Test Source">69eda27a-e346-46c5-b41b-64e4953de884</app-id>
          <person-id name="Test User">2d44d876-3bde-482b-a2af-ba133bc41fa9</person-id>
          <access-avenue>Offline</access-avenue>
          <audit-action>Created</audit-action>
          <master-app-id>30325d89-0308-4744-843f-c88599db77c7</master-app-id>
        </created>
        <updated>
          <timestamp>2017-02-08T23:01:03.543Z</timestamp>
          <app-id name="Test Source">69eda27a-e346-46c5-b41b-64e4953de884</app-id>
          <person-id name="Test User">2d44d876-3bde-482b-a2af-ba133bc41fa9</person-id>
          <access-avenue>Offline</access-avenue>
          <audit-action>Created</audit-action>
          <master-app-id>30325d89-0308-4744-843f-c88599db77c7</master-app-id>
        </updated>
        <data-xml>
          <blood-pressure>
            <when>
              <date>
                <y>2017</y>
                <m>2</m>
                <d>8</d>
              </date>
              <time>
                <h>15</h>
                <m>0</m>
                <s>57</s>
                <f>0</f>
              </time>
            </when>
            <systolic>101</systolic>
            <diastolic>91</diastolic>
            <pulse>80</pulse>
          </blood-pressure>
          <common />
        </data-xml>
        <eff-permissions immutable="false">
          <permission>Read</permission>
          <permission>Update</permission>
          <permission>Create</permission>
          <permission>Delete</permission>
        </eff-permissions>
      </thing>
      <thing>
        <thing-id version-stamp="7f1afebc-4130-4bef-a2ae-8bd98cc9b3da">fbc0a398-a87d-4125-a3d0-676c169f7a4d</thing-id>
        <type-id name="Blood pressure">ca3c57f4-f4c1-4e15-be67-0a3caf5414ed</type-id>
        <thing-state>Active</thing-state>
        <flags>0</flags>
        <eff-date>2017-02-08T14:44:35</eff-date>
        <created>
          <timestamp>2017-02-08T22:44:35.427Z</timestamp>
          <app-id name="Test Source">df8399dc-d3f7-4645-bf4a-31989f3464b3</app-id>
          <person-id name="Test User">2d44d876-3bde-482b-a2af-ba133bc41fa9</person-id>
          <access-avenue>Offline</access-avenue>
          <audit-action>Created</audit-action>
          <master-app-id>30325d89-0308-4744-843f-c88599db77c7</master-app-id>
        </created>
        <updated>
          <timestamp>2017-02-08T22:44:35.427Z</timestamp>
          <app-id name="Test Source">df8399dc-d3f7-4645-bf4a-31989f3464b3</app-id>
          <person-id name="Test User">2d44d876-3bde-482b-a2af-ba133bc41fa9</person-id>
          <access-avenue>Offline</access-avenue>
          <audit-action>Created</audit-action>
          <master-app-id>30325d89-0308-4744-843f-c88599db77c7</master-app-id>
        </updated>
        <data-xml>
          <blood-pressure>
            <when>
              <date>
                <y>2017</y>
                <m>2</m>
                <d>8</d>
              </date>
              <time>
                <h>14</h>
                <m>44</m>
                <s>35</s>
                <f>0</f>
              </time>
            </when>
            <systolic>101</systolic>
            <diastolic>90</diastolic>
            <pulse>80</pulse>
          </blood-pressure>
          <common />
        </data-xml>
        <eff-permissions immutable="false">
          <permission>Read</permission>
          <permission>Update</permission>
          <permission>Create</permission>
          <permission>Delete</permission>
        </eff-permissions>
      </thing>
      <thing>
        <thing-id version-stamp="0099c441-3966-4e43-8592-134876cc87e8">1995ac6d-21e9-4f29-adb5-8bbd7e0ea89c</thing-id>
        <type-id name="Contact">25c94a9f-9d3d-4576-96dc-6791178a8143</type-id>
        <thing-state>Active</thing-state>
        <flags>0</flags>
        <eff-date>2017-02-03T20:27:20.705</eff-date>
        <created>
          <timestamp>2017-02-03T20:27:20.417Z</timestamp>
          <app-id name="Test Source">72704e7a-0c9a-4c21-9094-33562c8327d5</app-id>
          <person-id name="Test User">2d44d876-3bde-482b-a2af-ba133bc41fa9</person-id>
          <access-avenue>Offline</access-avenue>
          <audit-action>Created</audit-action>
          <master-app-id>d6318dff-5352-4a10-a140-6c82c6536a3b</master-app-id>
        </created>
        <updated>
          <timestamp>2017-02-03T20:27:53.817Z</timestamp>
          <app-id name="Test Source">72704e7a-0c9a-4c21-9094-33562c8327d5</app-id>
          <person-id name="Test User">2d44d876-3bde-482b-a2af-ba133bc41fa9</person-id>
          <access-avenue>Offline</access-avenue>
          <audit-action>Updated</audit-action>
          <master-app-id>d6318dff-5352-4a10-a140-6c82c6536a3b</master-app-id>
        </updated>
        <data-xml>
          <person>
            <name>
              <full>Test User</full>
              <title>
                <text />
              </title>
              <first>will</first>
              <middle />
              <last>shelor</last>
              <suffix>
                <text />
              </suffix>
            </name>
            <contact />
            <type>
              <text />
            </type>
          </person>
          <common>
            <note />
          </common>
        </data-xml>
        <eff-permissions immutable="false">
          <permission>Read</permission>
          <permission>Update</permission>
          <permission>Create</permission>
          <permission>Delete</permission>
        </eff-permissions>
      </thing>
      <thing>
        <thing-id version-stamp="e37ae2ee-58da-4792-b7b5-62bbb3cc8cf1">ce47dbb4-f1e5-4802-9c23-531804bd8ef4</thing-id>
        <type-id name="Blood pressure">ca3c57f4-f4c1-4e15-be67-0a3caf5414ed</type-id>
        <thing-state>Active</thing-state>
        <flags>0</flags>
        <eff-date>2017-02-03T12:10:58</eff-date>
        <created>
          <timestamp>2017-02-03T20:10:58.437Z</timestamp>
          <app-id name="Test Source">72704e7a-0c9a-4c21-9094-33562c8327d5</app-id>
          <person-id name="Test User">2d44d876-3bde-482b-a2af-ba133bc41fa9</person-id>
          <access-avenue>Offline</access-avenue>
          <audit-action>Created</audit-action>
          <master-app-id>d6318dff-5352-4a10-a140-6c82c6536a3b</master-app-id>
        </created>
        <updated>
          <timestamp>2017-02-03T20:10:58.437Z</timestamp>
          <app-id name="Test Source">72704e7a-0c9a-4c21-9094-33562c8327d5</app-id>
          <person-id name="Test User">2d44d876-3bde-482b-a2af-ba133bc41fa9</person-id>
          <access-avenue>Offline</access-avenue>
          <audit-action>Created</audit-action>
          <master-app-id>d6318dff-5352-4a10-a140-6c82c6536a3b</master-app-id>
        </updated>
        <data-xml>
          <blood-pressure>
            <when>
              <date>
                <y>2017</y>
                <m>2</m>
                <d>3</d>
              </date>
              <time>
                <h>12</h>
                <m>10</m>
                <s>58</s>
                <f>0</f>
              </time>
            </when>
            <systolic>101</systolic>
            <diastolic>90</diastolic>
            <pulse>80</pulse>
          </blood-pressure>
          <common />
        </data-xml>
        <eff-permissions immutable="false">
          <permission>Read</permission>
          <permission>Update</permission>
          <permission>Create</permission>
          <permission>Delete</permission>
        </eff-permissions>
      </thing>
      <thing>
        <thing-id version-stamp="69a75f03-601d-44e0-bf69-63f63dfdc01b">a07ebab5-c161-440e-ac1c-3ade502ce24b</thing-id>
        <type-id name="Blood pressure">ca3c57f4-f4c1-4e15-be67-0a3caf5414ed</type-id>
        <thing-state>Active</thing-state>
        <flags>0</flags>
        <eff-date>2017-02-03T12:08:46</eff-date>
        <created>
          <timestamp>2017-02-03T20:08:46.727Z</timestamp>
          <app-id name="Test Source">72704e7a-0c9a-4c21-9094-33562c8327d5</app-id>
          <person-id name="Test User">2d44d876-3bde-482b-a2af-ba133bc41fa9</person-id>
          <access-avenue>Offline</access-avenue>
          <audit-action>Created</audit-action>
          <master-app-id>d6318dff-5352-4a10-a140-6c82c6536a3b</master-app-id>
        </created>
        <updated>
          <timestamp>2017-02-03T20:08:46.727Z</timestamp>
          <app-id name="Test Source">72704e7a-0c9a-4c21-9094-33562c8327d5</app-id>
          <person-id name="Test User">2d44d876-3bde-482b-a2af-ba133bc41fa9</person-id>
          <access-avenue>Offline</access-avenue>
          <audit-action>Created</audit-action>
          <master-app-id>d6318dff-5352-4a10-a140-6c82c6536a3b</master-app-id>
        </updated>
        <data-xml>
          <blood-pressure>
            <when>
              <date>
                <y>2017</y>
                <m>2</m>
                <d>3</d>
              </date>
              <time>
                <h>12</h>
                <m>8</m>
                <s>46</s>
                <f>0</f>
              </time>
            </when>
            <systolic>100</systolic>
            <diastolic>90</diastolic>
            <pulse>80</pulse>
          </blood-pressure>
          <common />
        </data-xml>
        <eff-permissions immutable="false">
          <permission>Read</permission>
          <permission>Update</permission>
          <permission>Create</permission>
          <permission>Delete</permission>
        </eff-permissions>
      </thing>
      <thing>
        <thing-id version-stamp="25c0af8b-abd8-477f-8bba-3b8f2b97356e">c708fff3-dc63-4b9e-9781-b3cd1505d3ac</thing-id>
        <type-id name="Blood pressure">ca3c57f4-f4c1-4e15-be67-0a3caf5414ed</type-id>
        <thing-state>Active</thing-state>
        <flags>0</flags>
        <eff-date>2017-01-26T10:55:39</eff-date>
        <created>
          <timestamp>2017-01-26T18:56:16.317Z</timestamp>
          <app-id name="Test Source">9f66b42f-a5f0-4290-81af-25b59149b585</app-id>
          <person-id name="Test User">2d44d876-3bde-482b-a2af-ba133bc41fa9</person-id>
          <access-avenue>Offline</access-avenue>
          <audit-action>Created</audit-action>
          <master-app-id>30325d89-0308-4744-843f-c88599db77c7</master-app-id>
        </created>
        <updated>
          <timestamp>2017-01-26T18:56:16.317Z</timestamp>
          <app-id name="Test Source">9f66b42f-a5f0-4290-81af-25b59149b585</app-id>
          <person-id name="Test User">2d44d876-3bde-482b-a2af-ba133bc41fa9</person-id>
          <access-avenue>Offline</access-avenue>
          <audit-action>Created</audit-action>
          <master-app-id>30325d89-0308-4744-843f-c88599db77c7</master-app-id>
        </updated>
        <data-xml>
          <blood-pressure>
            <when>
              <date>
                <y>2017</y>
                <m>1</m>
                <d>26</d>
              </date>
              <time>
                <h>10</h>
                <m>55</m>
                <s>39</s>
                <f>0</f>
              </time>
            </when>
            <systolic>127</systolic>
            <diastolic>82</diastolic>
            <pulse>71</pulse>
          </blood-pressure>
          <common />
        </data-xml>
        <eff-permissions immutable="false">
          <permission>Read</permission>
          <permission>Update</permission>
          <permission>Create</permission>
          <permission>Delete</permission>
        </eff-permissions>
      </thing>
      <thing>
        <thing-id version-stamp="5d78528f-aa51-4bbd-be92-c3cb1ffb3708">821ef4b2-caa0-4728-b568-7054be631fb6</thing-id>
        <type-id name="Blood pressure">ca3c57f4-f4c1-4e15-be67-0a3caf5414ed</type-id>
        <thing-state>Active</thing-state>
        <flags>0</flags>
        <eff-date>2017-01-25T22:13:44</eff-date>
        <created>
          <timestamp>2017-01-26T06:13:44.317Z</timestamp>
          <app-id name="Test Source">7636d965-7583-48ab-a61b-fa13db258bd8</app-id>
          <person-id name="Test User">2d44d876-3bde-482b-a2af-ba133bc41fa9</person-id>
          <access-avenue>Offline</access-avenue>
          <audit-action>Created</audit-action>
          <master-app-id>30325d89-0308-4744-843f-c88599db77c7</master-app-id>
        </created>
        <updated>
          <timestamp>2017-01-26T06:13:44.317Z</timestamp>
          <app-id name="Test Source">7636d965-7583-48ab-a61b-fa13db258bd8</app-id>
          <person-id name="Test User">2d44d876-3bde-482b-a2af-ba133bc41fa9</person-id>
          <access-avenue>Offline</access-avenue>
          <audit-action>Created</audit-action>
          <master-app-id>30325d89-0308-4744-843f-c88599db77c7</master-app-id>
        </updated>
        <data-xml>
          <blood-pressure>
            <when>
              <date>
                <y>2017</y>
                <m>1</m>
                <d>25</d>
              </date>
              <time>
                <h>22</h>
                <m>13</m>
                <s>44</s>
                <f>0</f>
              </time>
            </when>
            <systolic>120</systolic>
            <diastolic>80</diastolic>
            <pulse>64</pulse>
          </blood-pressure>
          <common />
        </data-xml>
        <eff-permissions immutable="false">
          <permission>Read</permission>
          <permission>Update</permission>
          <permission>Create</permission>
          <permission>Delete</permission>
        </eff-permissions>
      </thing>
      <thing>
        <thing-id version-stamp="60712cc2-24c0-4200-91f5-86592d7a3d4a">5eaf374c-f7bc-4e57-952a-e02964a7db5e</thing-id>
        <type-id name="Contact">25c94a9f-9d3d-4576-96dc-6791178a8143</type-id>
        <thing-state>Active</thing-state>
        <flags>0</flags>
        <eff-date>2017-01-11T00:09:49.801</eff-date>
        <created>
          <timestamp>2017-01-11T00:09:50.53Z</timestamp>
          <app-id name="Test Source">d158e9c6-02c9-4256-abf0-2deb05ede5fa</app-id>
          <person-id name="Test User">2d44d876-3bde-482b-a2af-ba133bc41fa9</person-id>
          <access-avenue>Offline</access-avenue>
          <audit-action>Created</audit-action>
          <master-app-id>d6318dff-5352-4a10-a140-6c82c6536a3b</master-app-id>
        </created>
        <updated>
          <timestamp>2017-01-11T00:09:50.53Z</timestamp>
          <app-id name="Test Source">d158e9c6-02c9-4256-abf0-2deb05ede5fa</app-id>
          <person-id name="Test User">2d44d876-3bde-482b-a2af-ba133bc41fa9</person-id>
          <access-avenue>Offline</access-avenue>
          <audit-action>Created</audit-action>
          <master-app-id>d6318dff-5352-4a10-a140-6c82c6536a3b</master-app-id>
        </updated>
        <data-xml>
          <person>
            <name>
              <full>bfgdhd</full>
              <title>
                <text />
              </title>
              <first />
              <middle />
              <last>bfgdhd</last>
              <suffix>
                <text />
              </suffix>
            </name>
            <professional-training>vdgsh</professional-training>
            <contact />
            <type>
              <text />
            </type>
          </person>
          <common>
            <note />
          </common>
        </data-xml>
        <eff-permissions immutable="false">
          <permission>Read</permission>
          <permission>Update</permission>
          <permission>Create</permission>
          <permission>Delete</permission>
        </eff-permissions>
      </thing>
      <thing>
        <thing-id version-stamp="bf954999-859f-478e-8bd4-a054784203ab">0da8a11b-d894-4a52-8c15-08589a3e8f48</thing-id>
        <type-id name="Blood pressure">ca3c57f4-f4c1-4e15-be67-0a3caf5414ed</type-id>
        <thing-state>Active</thing-state>
        <flags>0</flags>
        <eff-date>2016-12-21T20:15:52</eff-date>
        <created>
          <timestamp>2016-12-22T04:15:52.79Z</timestamp>
          <app-id name="Test Source">e3a153d5-f6be-44eb-b425-f9a79bc1cc1c</app-id>
          <person-id name="Test User">2d44d876-3bde-482b-a2af-ba133bc41fa9</person-id>
          <access-avenue>Offline</access-avenue>
          <audit-action>Created</audit-action>
          <master-app-id>30325d89-0308-4744-843f-c88599db77c7</master-app-id>
        </created>
        <updated>
          <timestamp>2016-12-22T04:15:52.79Z</timestamp>
          <app-id name="Test Source">e3a153d5-f6be-44eb-b425-f9a79bc1cc1c</app-id>
          <person-id name="Test User">2d44d876-3bde-482b-a2af-ba133bc41fa9</person-id>
          <access-avenue>Offline</access-avenue>
          <audit-action>Created</audit-action>
          <master-app-id>30325d89-0308-4744-843f-c88599db77c7</master-app-id>
        </updated>
        <data-xml>
          <blood-pressure>
            <when>
              <date>
                <y>2016</y>
                <m>12</m>
                <d>21</d>
              </date>
              <time>
                <h>20</h>
                <m>15</m>
                <s>52</s>
                <f>0</f>
              </time>
            </when>
            <systolic>110</systolic>
            <diastolic>70</diastolic>
            <pulse>61</pulse>
          </blood-pressure>
          <common />
        </data-xml>
        <eff-permissions immutable="false">
          <permission>Read</permission>
          <permission>Update</permission>
          <permission>Create</permission>
          <permission>Delete</permission>
        </eff-permissions>
      </thing>
      <thing>
        <thing-id version-stamp="13a88459-f9cd-48d1-95b2-616d0cf58393">288d8a39-555e-4434-b5a9-5d806d851697</thing-id>
        <type-id name="Blood pressure">ca3c57f4-f4c1-4e15-be67-0a3caf5414ed</type-id>
        <thing-state>Active</thing-state>
        <flags>0</flags>
        <eff-date>2016-12-21T20:11:15</eff-date>
        <created>
          <timestamp>2016-12-22T04:11:16Z</timestamp>
          <app-id name="Test Source">e3a153d5-f6be-44eb-b425-f9a79bc1cc1c</app-id>
          <person-id name="Test User">2d44d876-3bde-482b-a2af-ba133bc41fa9</person-id>
          <access-avenue>Offline</access-avenue>
          <audit-action>Created</audit-action>
          <master-app-id>30325d89-0308-4744-843f-c88599db77c7</master-app-id>
        </created>
        <updated>
          <timestamp>2016-12-22T04:11:16Z</timestamp>
          <app-id name="Test Source">e3a153d5-f6be-44eb-b425-f9a79bc1cc1c</app-id>
          <person-id name="Test User">2d44d876-3bde-482b-a2af-ba133bc41fa9</person-id>
          <access-avenue>Offline</access-avenue>
          <audit-action>Created</audit-action>
          <master-app-id>30325d89-0308-4744-843f-c88599db77c7</master-app-id>
        </updated>
        <data-xml>
          <blood-pressure>
            <when>
              <date>
                <y>2016</y>
                <m>12</m>
                <d>21</d>
              </date>
              <time>
                <h>20</h>
                <m>11</m>
                <s>15</s>
                <f>0</f>
              </time>
            </when>
            <systolic>110</systolic>
            <diastolic>70</diastolic>
            <pulse>61</pulse>
          </blood-pressure>
          <common />
        </data-xml>
        <eff-permissions immutable="false">
          <permission>Read</permission>
          <permission>Update</permission>
          <permission>Create</permission>
          <permission>Delete</permission>
        </eff-permissions>
      </thing>
      <thing>
        <thing-id version-stamp="3babbd10-a34c-4b81-8695-ae0c336b6df1">2abf76e3-a819-443e-bda9-29d98f0aff4b</thing-id>
        <type-id name="Blood pressure">ca3c57f4-f4c1-4e15-be67-0a3caf5414ed</type-id>
        <thing-state>Active</thing-state>
        <flags>0</flags>
        <eff-date>2016-09-12T15:23:52.817</eff-date>
        <created>
          <timestamp>2016-09-12T22:23:50.66Z</timestamp>
          <app-id name="Test Source">a5e11c0c-a0f8-479e-98a8-7db4838903f4</app-id>
          <person-id name="Test User">2d44d876-3bde-482b-a2af-ba133bc41fa9</person-id>
          <access-avenue>Offline</access-avenue>
          <audit-action>Created</audit-action>
          <master-app-id>5f2ece6b-6a74-4d39-8312-91d86df7e2db</master-app-id>
        </created>
        <updated>
          <timestamp>2016-09-12T22:23:50.66Z</timestamp>
          <app-id name="Test Source">a5e11c0c-a0f8-479e-98a8-7db4838903f4</app-id>
          <person-id name="Test User">2d44d876-3bde-482b-a2af-ba133bc41fa9</person-id>
          <access-avenue>Offline</access-avenue>
          <audit-action>Created</audit-action>
          <master-app-id>5f2ece6b-6a74-4d39-8312-91d86df7e2db</master-app-id>
        </updated>
        <data-xml>
          <blood-pressure>
            <when>
              <date>
                <y>2016</y>
                <m>9</m>
                <d>12</d>
              </date>
              <time>
                <h>15</h>
                <m>23</m>
                <s>52</s>
                <f>817</f>
              </time>
            </when>
            <systolic>114</systolic>
            <diastolic>70</diastolic>
            <pulse>61</pulse>
          </blood-pressure>
          <common />
        </data-xml>
        <eff-permissions immutable="false">
          <permission>Read</permission>
          <permission>Update</permission>
          <permission>Create</permission>
          <permission>Delete</permission>
        </eff-permissions>
      </thing>
      <thing>
        <thing-id version-stamp="62b9bfdd-9e69-4011-853a-7174fab31142">15361567-bd95-4987-b06f-8939df98931b</thing-id>
        <type-id name="Blood pressure">ca3c57f4-f4c1-4e15-be67-0a3caf5414ed</type-id>
        <thing-state>Active</thing-state>
        <flags>0</flags>
        <eff-date>2016-09-07T14:08:41.952</eff-date>
        <created>
          <timestamp>2016-09-07T21:08:41.07Z</timestamp>
          <app-id name="Test Source">027a4609-1704-4cfc-8d06-f91238805174</app-id>
          <person-id name="Test User">2d44d876-3bde-482b-a2af-ba133bc41fa9</person-id>
          <access-avenue>Offline</access-avenue>
          <audit-action>Created</audit-action>
          <master-app-id>5f2ece6b-6a74-4d39-8312-91d86df7e2db</master-app-id>
        </created>
        <updated>
          <timestamp>2016-09-07T21:08:41.07Z</timestamp>
          <app-id name="Test Source">027a4609-1704-4cfc-8d06-f91238805174</app-id>
          <person-id name="Test User">2d44d876-3bde-482b-a2af-ba133bc41fa9</person-id>
          <access-avenue>Offline</access-avenue>
          <audit-action>Created</audit-action>
          <master-app-id>5f2ece6b-6a74-4d39-8312-91d86df7e2db</master-app-id>
        </updated>
        <data-xml>
          <blood-pressure>
            <when>
              <date>
                <y>2016</y>
                <m>9</m>
                <d>7</d>
              </date>
              <time>
                <h>14</h>
                <m>8</m>
                <s>41</s>
                <f>952</f>
              </time>
            </when>
            <systolic>120</systolic>
            <diastolic>80</diastolic>
            <pulse>64</pulse>
          </blood-pressure>
          <common />
        </data-xml>
        <eff-permissions immutable="false">
          <permission>Read</permission>
          <permission>Update</permission>
          <permission>Create</permission>
          <permission>Delete</permission>
        </eff-permissions>
      </thing>
      <thing>
        <thing-id version-stamp="08db8cb9-1d70-4252-a529-580a9f94a34d">9dcb0311-0649-4b1d-becc-db88c3e842c8</thing-id>
        <type-id name="Blood pressure">ca3c57f4-f4c1-4e15-be67-0a3caf5414ed</type-id>
        <thing-state>Active</thing-state>
        <flags>0</flags>
        <eff-date>2016-09-07T13:35:12.791</eff-date>
        <created>
          <timestamp>2016-09-07T20:35:12.267Z</timestamp>
          <app-id name="Test Source">027a4609-1704-4cfc-8d06-f91238805174</app-id>
          <person-id name="Test User">2d44d876-3bde-482b-a2af-ba133bc41fa9</person-id>
          <access-avenue>Offline</access-avenue>
          <audit-action>Created</audit-action>
          <master-app-id>5f2ece6b-6a74-4d39-8312-91d86df7e2db</master-app-id>
        </created>
        <updated>
          <timestamp>2016-09-07T20:35:12.267Z</timestamp>
          <app-id name="Test Source">027a4609-1704-4cfc-8d06-f91238805174</app-id>
          <person-id name="Test User">2d44d876-3bde-482b-a2af-ba133bc41fa9</person-id>
          <access-avenue>Offline</access-avenue>
          <audit-action>Created</audit-action>
          <master-app-id>5f2ece6b-6a74-4d39-8312-91d86df7e2db</master-app-id>
        </updated>
        <data-xml>
          <blood-pressure>
            <when>
              <date>
                <y>2016</y>
                <m>9</m>
                <d>7</d>
              </date>
              <time>
                <h>13</h>
                <m>35</m>
                <s>12</s>
                <f>791</f>
              </time>
            </when>
            <systolic>125</systolic>
            <diastolic>97</diastolic>
            <pulse>82</pulse>
          </blood-pressure>
          <common />
        </data-xml>
        <eff-permissions immutable="false">
          <permission>Read</permission>
          <permission>Update</permission>
          <permission>Create</permission>
          <permission>Delete</permission>
        </eff-permissions>
      </thing>
      <thing>
        <thing-id version-stamp="7b460e44-8115-4eca-b021-7518a1374baa">a598674b-b085-4d34-8d2d-03a488c1847b</thing-id>
        <type-id name="Blood pressure">ca3c57f4-f4c1-4e15-be67-0a3caf5414ed</type-id>
        <thing-state>Active</thing-state>
        <flags>0</flags>
        <eff-date>2016-09-07T11:50:50.023</eff-date>
        <created>
          <timestamp>2016-09-07T18:50:49.113Z</timestamp>
          <app-id name="Test Source">95519473-5fca-4c0f-9fc8-b67abce47507</app-id>
          <person-id name="Test User">2d44d876-3bde-482b-a2af-ba133bc41fa9</person-id>
          <access-avenue>Offline</access-avenue>
          <audit-action>Created</audit-action>
          <master-app-id>5f2ece6b-6a74-4d39-8312-91d86df7e2db</master-app-id>
        </created>
        <updated>
          <timestamp>2016-09-07T18:50:49.113Z</timestamp>
          <app-id name="Test Source">95519473-5fca-4c0f-9fc8-b67abce47507</app-id>
          <person-id name="Test User">2d44d876-3bde-482b-a2af-ba133bc41fa9</person-id>
          <access-avenue>Offline</access-avenue>
          <audit-action>Created</audit-action>
          <master-app-id>5f2ece6b-6a74-4d39-8312-91d86df7e2db</master-app-id>
        </updated>
        <data-xml>
          <blood-pressure>
            <when>
              <date>
                <y>2016</y>
                <m>9</m>
                <d>7</d>
              </date>
              <time>
                <h>11</h>
                <m>50</m>
                <s>50</s>
                <f>23</f>
              </time>
            </when>
            <systolic>120</systolic>
            <diastolic>80</diastolic>
            <pulse>64</pulse>
          </blood-pressure>
          <common />
        </data-xml>
        <eff-permissions immutable="false">
          <permission>Read</permission>
          <permission>Update</permission>
          <permission>Create</permission>
          <permission>Delete</permission>
        </eff-permissions>
      </thing>
      <thing>
        <thing-id version-stamp="593150b0-386a-4e36-b563-dafa68be2fad">c4eb4a0d-14c6-43e9-b6bf-f0c171044b22</thing-id>
        <type-id name="Blood pressure">ca3c57f4-f4c1-4e15-be67-0a3caf5414ed</type-id>
        <thing-state>Active</thing-state>
        <flags>0</flags>
        <eff-date>2016-09-07T11:48:39.815</eff-date>
        <created>
          <timestamp>2016-09-07T18:48:38.857Z</timestamp>
          <app-id name="Test Source">95519473-5fca-4c0f-9fc8-b67abce47507</app-id>
          <person-id name="Test User">2d44d876-3bde-482b-a2af-ba133bc41fa9</person-id>
          <access-avenue>Offline</access-avenue>
          <audit-action>Created</audit-action>
          <master-app-id>5f2ece6b-6a74-4d39-8312-91d86df7e2db</master-app-id>
        </created>
        <updated>
          <timestamp>2016-09-07T18:48:38.857Z</timestamp>
          <app-id name="Test Source">95519473-5fca-4c0f-9fc8-b67abce47507</app-id>
          <person-id name="Test User">2d44d876-3bde-482b-a2af-ba133bc41fa9</person-id>
          <access-avenue>Offline</access-avenue>
          <audit-action>Created</audit-action>
          <master-app-id>5f2ece6b-6a74-4d39-8312-91d86df7e2db</master-app-id>
        </updated>
        <data-xml>
          <blood-pressure>
            <when>
              <date>
                <y>2016</y>
                <m>9</m>
                <d>7</d>
              </date>
              <time>
                <h>11</h>
                <m>48</m>
                <s>39</s>
                <f>815</f>
              </time>
            </when>
            <systolic>120</systolic>
            <diastolic>80</diastolic>
            <pulse>64</pulse>
          </blood-pressure>
          <common />
        </data-xml>
        <eff-permissions immutable="false">
          <permission>Read</permission>
          <permission>Update</permission>
          <permission>Create</permission>
          <permission>Delete</permission>
        </eff-permissions>
      </thing>
      <thing>
        <thing-id version-stamp="25abd99d-902c-44f9-b98a-0b0cfd10b38b">1fddae4e-00c2-4fb9-ba2f-4b366951281b</thing-id>
        <type-id name="Blood pressure">ca3c57f4-f4c1-4e15-be67-0a3caf5414ed</type-id>
        <thing-state>Active</thing-state>
        <flags>0</flags>
        <eff-date>2016-09-06T19:17:49.189</eff-date>
        <created>
          <timestamp>2016-09-07T02:17:50.13Z</timestamp>
          <app-id name="Test Source">95519473-5fca-4c0f-9fc8-b67abce47507</app-id>
          <person-id name="Test User">2d44d876-3bde-482b-a2af-ba133bc41fa9</person-id>
          <access-avenue>Offline</access-avenue>
          <audit-action>Created</audit-action>
          <master-app-id>5f2ece6b-6a74-4d39-8312-91d86df7e2db</master-app-id>
        </created>
        <updated>
          <timestamp>2016-09-07T02:17:50.13Z</timestamp>
          <app-id name="Test Source">95519473-5fca-4c0f-9fc8-b67abce47507</app-id>
          <person-id name="Test User">2d44d876-3bde-482b-a2af-ba133bc41fa9</person-id>
          <access-avenue>Offline</access-avenue>
          <audit-action>Created</audit-action>
          <master-app-id>5f2ece6b-6a74-4d39-8312-91d86df7e2db</master-app-id>
        </updated>
        <data-xml>
          <blood-pressure>
            <when>
              <date>
                <y>2016</y>
                <m>9</m>
                <d>6</d>
              </date>
              <time>
                <h>19</h>
                <m>17</m>
                <s>49</s>
                <f>189</f>
              </time>
            </when>
            <systolic>120</systolic>
            <diastolic>80</diastolic>
            <pulse>64</pulse>
          </blood-pressure>
          <common />
        </data-xml>
        <eff-permissions immutable="false">
          <permission>Read</permission>
          <permission>Update</permission>
          <permission>Create</permission>
          <permission>Delete</permission>
        </eff-permissions>
      </thing>
      <thing>
        <thing-id version-stamp="fa324e44-f487-403c-9f3f-1e1d862c76ba">5d75e2cd-3400-424a-82e4-f02e850c480e</thing-id>
        <type-id name="Blood pressure">ca3c57f4-f4c1-4e15-be67-0a3caf5414ed</type-id>
        <thing-state>Active</thing-state>
        <flags>0</flags>
        <eff-date>2016-09-06T17:00:10.894</eff-date>
        <created>
          <timestamp>2016-09-07T00:00:11.653Z</timestamp>
          <app-id name="Test Source">823a2595-7644-41cf-9242-8498d6a6d0db</app-id>
          <person-id name="Test User">2d44d876-3bde-482b-a2af-ba133bc41fa9</person-id>
          <access-avenue>Offline</access-avenue>
          <audit-action>Created</audit-action>
          <master-app-id>5f2ece6b-6a74-4d39-8312-91d86df7e2db</master-app-id>
        </created>
        <updated>
          <timestamp>2016-09-07T00:00:11.653Z</timestamp>
          <app-id name="Test Source">823a2595-7644-41cf-9242-8498d6a6d0db</app-id>
          <person-id name="Test User">2d44d876-3bde-482b-a2af-ba133bc41fa9</person-id>
          <access-avenue>Offline</access-avenue>
          <audit-action>Created</audit-action>
          <master-app-id>5f2ece6b-6a74-4d39-8312-91d86df7e2db</master-app-id>
        </updated>
        <data-xml>
          <blood-pressure>
            <when>
              <date>
                <y>2016</y>
                <m>9</m>
                <d>6</d>
              </date>
              <time>
                <h>17</h>
                <m>0</m>
                <s>10</s>
                <f>894</f>
              </time>
            </when>
            <systolic>120</systolic>
            <diastolic>80</diastolic>
            <pulse>64</pulse>
          </blood-pressure>
          <common />
        </data-xml>
        <eff-permissions immutable="false">
          <permission>Read</permission>
          <permission>Update</permission>
          <permission>Create</permission>
          <permission>Delete</permission>
        </eff-permissions>
      </thing>
      <thing>
        <thing-id version-stamp="ee538abb-d128-48d9-87b5-e9af3bc05546">a4184c6e-6e93-4693-945c-8b123dc9fe75</thing-id>
        <type-id name="Blood pressure">ca3c57f4-f4c1-4e15-be67-0a3caf5414ed</type-id>
        <thing-state>Active</thing-state>
        <flags>0</flags>
        <eff-date>2016-09-06T16:26:14.354</eff-date>
        <created>
          <timestamp>2016-09-06T23:26:14.987Z</timestamp>
          <app-id name="Test Source">95519473-5fca-4c0f-9fc8-b67abce47507</app-id>
          <person-id name="Test User">2d44d876-3bde-482b-a2af-ba133bc41fa9</person-id>
          <access-avenue>Offline</access-avenue>
          <audit-action>Created</audit-action>
          <master-app-id>5f2ece6b-6a74-4d39-8312-91d86df7e2db</master-app-id>
        </created>
        <updated>
          <timestamp>2016-09-06T23:26:14.987Z</timestamp>
          <app-id name="Test Source">95519473-5fca-4c0f-9fc8-b67abce47507</app-id>
          <person-id name="Test User">2d44d876-3bde-482b-a2af-ba133bc41fa9</person-id>
          <access-avenue>Offline</access-avenue>
          <audit-action>Created</audit-action>
          <master-app-id>5f2ece6b-6a74-4d39-8312-91d86df7e2db</master-app-id>
        </updated>
        <data-xml>
          <blood-pressure>
            <when>
              <date>
                <y>2016</y>
                <m>9</m>
                <d>6</d>
              </date>
              <time>
                <h>16</h>
                <m>26</m>
                <s>14</s>
                <f>354</f>
              </time>
            </when>
            <systolic>110</systolic>
            <diastolic>85</diastolic>
            <pulse>73</pulse>
          </blood-pressure>
          <common />
        </data-xml>
        <eff-permissions immutable="false">
          <permission>Read</permission>
          <permission>Update</permission>
          <permission>Create</permission>
          <permission>Delete</permission>
        </eff-permissions>
      </thing>
      <thing>
        <thing-id version-stamp="7cda809d-45c9-4d06-a956-a1835811921e">6a45ce04-792a-4fa9-a26b-3ee55daeef7f</thing-id>
        <type-id name="Blood pressure">ca3c57f4-f4c1-4e15-be67-0a3caf5414ed</type-id>
        <thing-state>Active</thing-state>
        <flags>0</flags>
        <eff-date>2016-09-06T16:19:43.933</eff-date>
        <created>
          <timestamp>2016-09-06T23:19:44.493Z</timestamp>
          <app-id name="Test Source">95519473-5fca-4c0f-9fc8-b67abce47507</app-id>
          <person-id name="Test User">2d44d876-3bde-482b-a2af-ba133bc41fa9</person-id>
          <access-avenue>Offline</access-avenue>
          <audit-action>Created</audit-action>
          <master-app-id>5f2ece6b-6a74-4d39-8312-91d86df7e2db</master-app-id>
        </created>
        <updated>
          <timestamp>2016-09-06T23:19:44.493Z</timestamp>
          <app-id name="Test Source">95519473-5fca-4c0f-9fc8-b67abce47507</app-id>
          <person-id name="Test User">2d44d876-3bde-482b-a2af-ba133bc41fa9</person-id>
          <access-avenue>Offline</access-avenue>
          <audit-action>Created</audit-action>
          <master-app-id>5f2ece6b-6a74-4d39-8312-91d86df7e2db</master-app-id>
        </updated>
        <data-xml>
          <blood-pressure>
            <when>
              <date>
                <y>2016</y>
                <m>9</m>
                <d>6</d>
              </date>
              <time>
                <h>16</h>
                <m>19</m>
                <s>43</s>
                <f>933</f>
              </time>
            </when>
            <systolic>107</systolic>
            <diastolic>81</diastolic>
            <pulse>67</pulse>
          </blood-pressure>
          <common />
        </data-xml>
        <eff-permissions immutable="false">
          <permission>Read</permission>
          <permission>Update</permission>
          <permission>Create</permission>
          <permission>Delete</permission>
        </eff-permissions>
      </thing>
      <thing>
        <thing-id version-stamp="6f555576-32cf-4aae-98a5-33dc67137f42">0d652490-f54c-452a-893b-20b2d49f3dad</thing-id>
        <type-id name="Blood pressure">ca3c57f4-f4c1-4e15-be67-0a3caf5414ed</type-id>
        <thing-state>Active</thing-state>
        <flags>0</flags>
        <eff-date>2016-09-06T16:18:06.106</eff-date>
        <created>
          <timestamp>2016-09-06T23:18:06.733Z</timestamp>
          <app-id name="Test Source">95519473-5fca-4c0f-9fc8-b67abce47507</app-id>
          <person-id name="Test User">2d44d876-3bde-482b-a2af-ba133bc41fa9</person-id>
          <access-avenue>Offline</access-avenue>
          <audit-action>Created</audit-action>
          <master-app-id>5f2ece6b-6a74-4d39-8312-91d86df7e2db</master-app-id>
        </created>
        <updated>
          <timestamp>2016-09-06T23:18:06.733Z</timestamp>
          <app-id name="Test Source">95519473-5fca-4c0f-9fc8-b67abce47507</app-id>
          <person-id name="Test User">2d44d876-3bde-482b-a2af-ba133bc41fa9</person-id>
          <access-avenue>Offline</access-avenue>
          <audit-action>Created</audit-action>
          <master-app-id>5f2ece6b-6a74-4d39-8312-91d86df7e2db</master-app-id>
        </updated>
        <data-xml>
          <blood-pressure>
            <when>
              <date>
                <y>2016</y>
                <m>9</m>
                <d>6</d>
              </date>
              <time>
                <h>16</h>
                <m>18</m>
                <s>6</s>
                <f>106</f>
              </time>
            </when>
            <systolic>120</systolic>
            <diastolic>80</diastolic>
            <pulse>64</pulse>
          </blood-pressure>
          <common />
        </data-xml>
        <eff-permissions immutable="false">
          <permission>Read</permission>
          <permission>Update</permission>
          <permission>Create</permission>
          <permission>Delete</permission>
        </eff-permissions>
      </thing>
      <thing>
        <thing-id version-stamp="c5c2feed-49b5-470c-b1f6-ae972168cdef">fd753431-6a12-489d-91e7-1cc68ea59907</thing-id>
        <type-id name="Blood pressure">ca3c57f4-f4c1-4e15-be67-0a3caf5414ed</type-id>
        <thing-state>Active</thing-state>
        <flags>0</flags>
        <eff-date>2016-09-06T12:02:03.743</eff-date>
        <created>
          <timestamp>2016-09-06T19:02:04.283Z</timestamp>
          <app-id name="Test Source">95519473-5fca-4c0f-9fc8-b67abce47507</app-id>
          <person-id name="Test User">2d44d876-3bde-482b-a2af-ba133bc41fa9</person-id>
          <access-avenue>Offline</access-avenue>
          <audit-action>Created</audit-action>
          <master-app-id>5f2ece6b-6a74-4d39-8312-91d86df7e2db</master-app-id>
        </created>
        <updated>
          <timestamp>2016-09-06T19:02:04.283Z</timestamp>
          <app-id name="Test Source">95519473-5fca-4c0f-9fc8-b67abce47507</app-id>
          <person-id name="Test User">2d44d876-3bde-482b-a2af-ba133bc41fa9</person-id>
          <access-avenue>Offline</access-avenue>
          <audit-action>Created</audit-action>
          <master-app-id>5f2ece6b-6a74-4d39-8312-91d86df7e2db</master-app-id>
        </updated>
        <data-xml>
          <blood-pressure>
            <when>
              <date>
                <y>2016</y>
                <m>9</m>
                <d>6</d>
              </date>
              <time>
                <h>12</h>
                <m>2</m>
                <s>3</s>
                <f>743</f>
              </time>
            </when>
            <systolic>120</systolic>
            <diastolic>80</diastolic>
            <pulse>64</pulse>
          </blood-pressure>
          <common />
        </data-xml>
        <eff-permissions immutable="false">
          <permission>Read</permission>
          <permission>Update</permission>
          <permission>Create</permission>
          <permission>Delete</permission>
        </eff-permissions>
      </thing>
      <thing>
        <thing-id version-stamp="5477ac5e-862a-4172-81d9-7dfc53008bcf">515c9ee7-fd33-4596-b4f5-894e6262fbe7</thing-id>
        <type-id name="Blood pressure">ca3c57f4-f4c1-4e15-be67-0a3caf5414ed</type-id>
        <thing-state>Active</thing-state>
        <flags>0</flags>
        <eff-date>2016-09-06T12:01:22.432</eff-date>
        <created>
          <timestamp>2016-09-06T19:01:23.08Z</timestamp>
          <app-id name="Test Source">95519473-5fca-4c0f-9fc8-b67abce47507</app-id>
          <person-id name="Test User">2d44d876-3bde-482b-a2af-ba133bc41fa9</person-id>
          <access-avenue>Offline</access-avenue>
          <audit-action>Created</audit-action>
          <master-app-id>5f2ece6b-6a74-4d39-8312-91d86df7e2db</master-app-id>
        </created>
        <updated>
          <timestamp>2016-09-06T19:01:23.08Z</timestamp>
          <app-id name="Test Source">95519473-5fca-4c0f-9fc8-b67abce47507</app-id>
          <person-id name="Test User">2d44d876-3bde-482b-a2af-ba133bc41fa9</person-id>
          <access-avenue>Offline</access-avenue>
          <audit-action>Created</audit-action>
          <master-app-id>5f2ece6b-6a74-4d39-8312-91d86df7e2db</master-app-id>
        </updated>
        <data-xml>
          <blood-pressure>
            <when>
              <date>
                <y>2016</y>
                <m>9</m>
                <d>6</d>
              </date>
              <time>
                <h>12</h>
                <m>1</m>
                <s>22</s>
                <f>432</f>
              </time>
            </when>
            <systolic>120</systolic>
            <diastolic>80</diastolic>
            <pulse>64</pulse>
          </blood-pressure>
          <common />
        </data-xml>
        <eff-permissions immutable="false">
          <permission>Read</permission>
          <permission>Update</permission>
          <permission>Create</permission>
          <permission>Delete</permission>
        </eff-permissions>
      </thing>
      <thing>
        <thing-id version-stamp="7d8c2f20-c780-47b5-9358-96b074608f3a">d2d7d0b3-e265-4ae7-9a41-b214343ca0a8</thing-id>
        <type-id name="Blood pressure">ca3c57f4-f4c1-4e15-be67-0a3caf5414ed</type-id>
        <thing-state>Active</thing-state>
        <flags>0</flags>
        <eff-date>2016-09-06T11:37:05.96</eff-date>
        <created>
          <timestamp>2016-09-06T18:37:06.553Z</timestamp>
          <app-id name="Test Source">95519473-5fca-4c0f-9fc8-b67abce47507</app-id>
          <person-id name="Test User">2d44d876-3bde-482b-a2af-ba133bc41fa9</person-id>
          <access-avenue>Offline</access-avenue>
          <audit-action>Created</audit-action>
          <master-app-id>5f2ece6b-6a74-4d39-8312-91d86df7e2db</master-app-id>
        </created>
        <updated>
          <timestamp>2016-09-06T18:37:06.553Z</timestamp>
          <app-id name="Test Source">95519473-5fca-4c0f-9fc8-b67abce47507</app-id>
          <person-id name="Test User">2d44d876-3bde-482b-a2af-ba133bc41fa9</person-id>
          <access-avenue>Offline</access-avenue>
          <audit-action>Created</audit-action>
          <master-app-id>5f2ece6b-6a74-4d39-8312-91d86df7e2db</master-app-id>
        </updated>
        <data-xml>
          <blood-pressure>
            <when>
              <date>
                <y>2016</y>
                <m>9</m>
                <d>6</d>
              </date>
              <time>
                <h>11</h>
                <m>37</m>
                <s>5</s>
                <f>960</f>
              </time>
            </when>
            <systolic>120</systolic>
            <diastolic>80</diastolic>
            <pulse>64</pulse>
          </blood-pressure>
          <common />
        </data-xml>
        <eff-permissions immutable="false">
          <permission>Read</permission>
          <permission>Update</permission>
          <permission>Create</permission>
          <permission>Delete</permission>
        </eff-permissions>
      </thing>
      <thing>
        <thing-id version-stamp="4076243d-441e-4c53-aeba-c1d13d1e6fd3">6a5700b8-c88f-4bb3-be17-3bba156a6338</thing-id>
        <type-id name="Blood pressure">ca3c57f4-f4c1-4e15-be67-0a3caf5414ed</type-id>
        <thing-state>Active</thing-state>
        <flags>0</flags>
        <eff-date>2016-09-02T16:07:13.771</eff-date>
        <created>
          <timestamp>2016-09-02T23:07:14.913Z</timestamp>
          <app-id name="Test Source">a94c245b-cd74-4fdf-bfaf-b6d8df05c27b</app-id>
          <person-id name="Test User">2d44d876-3bde-482b-a2af-ba133bc41fa9</person-id>
          <access-avenue>Offline</access-avenue>
          <audit-action>Created</audit-action>
          <master-app-id>5f2ece6b-6a74-4d39-8312-91d86df7e2db</master-app-id>
        </created>
        <updated>
          <timestamp>2016-09-02T23:07:14.913Z</timestamp>
          <app-id name="Test Source">a94c245b-cd74-4fdf-bfaf-b6d8df05c27b</app-id>
          <person-id name="Test User">2d44d876-3bde-482b-a2af-ba133bc41fa9</person-id>
          <access-avenue>Offline</access-avenue>
          <audit-action>Created</audit-action>
          <master-app-id>5f2ece6b-6a74-4d39-8312-91d86df7e2db</master-app-id>
        </updated>
        <data-xml>
          <blood-pressure>
            <when>
              <date>
                <y>2016</y>
                <m>9</m>
                <d>2</d>
              </date>
              <time>
                <h>16</h>
                <m>7</m>
                <s>13</s>
                <f>771</f>
              </time>
            </when>
            <systolic>120</systolic>
            <diastolic>80</diastolic>
            <pulse>64</pulse>
          </blood-pressure>
          <common />
        </data-xml>
        <eff-permissions immutable="false">
          <permission>Read</permission>
          <permission>Update</permission>
          <permission>Create</permission>
          <permission>Delete</permission>
        </eff-permissions>
      </thing>
      <thing>
        <thing-id version-stamp="e424109b-37be-49bd-bd16-5559c5d9c48c">7336c2c3-6b09-4582-93e5-cf7efeaaa4fe</thing-id>
        <type-id name="Blood pressure">ca3c57f4-f4c1-4e15-be67-0a3caf5414ed</type-id>
        <thing-state>Active</thing-state>
        <flags>0</flags>
        <eff-date>2016-09-02T14:49:24.424</eff-date>
        <created>
          <timestamp>2016-09-02T21:49:26.153Z</timestamp>
          <app-id name="Test Source">a94c245b-cd74-4fdf-bfaf-b6d8df05c27b</app-id>
          <person-id name="Test User">2d44d876-3bde-482b-a2af-ba133bc41fa9</person-id>
          <access-avenue>Offline</access-avenue>
          <audit-action>Created</audit-action>
          <master-app-id>5f2ece6b-6a74-4d39-8312-91d86df7e2db</master-app-id>
        </created>
        <updated>
          <timestamp>2016-09-02T21:49:26.153Z</timestamp>
          <app-id name="Test Source">a94c245b-cd74-4fdf-bfaf-b6d8df05c27b</app-id>
          <person-id name="Test User">2d44d876-3bde-482b-a2af-ba133bc41fa9</person-id>
          <access-avenue>Offline</access-avenue>
          <audit-action>Created</audit-action>
          <master-app-id>5f2ece6b-6a74-4d39-8312-91d86df7e2db</master-app-id>
        </updated>
        <data-xml>
          <blood-pressure>
            <when>
              <date>
                <y>2016</y>
                <m>9</m>
                <d>2</d>
              </date>
              <time>
                <h>14</h>
                <m>49</m>
                <s>24</s>
                <f>424</f>
              </time>
            </when>
            <systolic>120</systolic>
            <diastolic>80</diastolic>
            <pulse>64</pulse>
          </blood-pressure>
          <common />
        </data-xml>
        <eff-permissions immutable="false">
          <permission>Read</permission>
          <permission>Update</permission>
          <permission>Create</permission>
          <permission>Delete</permission>
        </eff-permissions>
      </thing>
      <thing>
        <thing-id version-stamp="b3b7ebe0-ab6d-4761-861a-cf6817ffbfef">544974de-0fa5-4d50-9efd-826d8e4c39a7</thing-id>
        <type-id name="Blood pressure">ca3c57f4-f4c1-4e15-be67-0a3caf5414ed</type-id>
        <thing-state>Active</thing-state>
        <flags>0</flags>
        <eff-date>2016-09-01T18:41:33.536</eff-date>
        <created>
          <timestamp>2016-09-02T01:41:34.793Z</timestamp>
          <app-id name="Test Source">a94c245b-cd74-4fdf-bfaf-b6d8df05c27b</app-id>
          <person-id name="Test User">2d44d876-3bde-482b-a2af-ba133bc41fa9</person-id>
          <access-avenue>Offline</access-avenue>
          <audit-action>Created</audit-action>
          <master-app-id>5f2ece6b-6a74-4d39-8312-91d86df7e2db</master-app-id>
        </created>
        <updated>
          <timestamp>2016-09-02T01:41:34.793Z</timestamp>
          <app-id name="Test Source">a94c245b-cd74-4fdf-bfaf-b6d8df05c27b</app-id>
          <person-id name="Test User">2d44d876-3bde-482b-a2af-ba133bc41fa9</person-id>
          <access-avenue>Offline</access-avenue>
          <audit-action>Created</audit-action>
          <master-app-id>5f2ece6b-6a74-4d39-8312-91d86df7e2db</master-app-id>
        </updated>
        <data-xml>
          <blood-pressure>
            <when>
              <date>
                <y>2016</y>
                <m>9</m>
                <d>1</d>
              </date>
              <time>
                <h>18</h>
                <m>41</m>
                <s>33</s>
                <f>536</f>
              </time>
            </when>
            <systolic>120</systolic>
            <diastolic>80</diastolic>
            <pulse>64</pulse>
          </blood-pressure>
          <common />
        </data-xml>
        <eff-permissions immutable="false">
          <permission>Read</permission>
          <permission>Update</permission>
          <permission>Create</permission>
          <permission>Delete</permission>
        </eff-permissions>
      </thing>
      <thing>
        <thing-id version-stamp="e4ad268c-f697-4cef-ab96-158ffc0c26eb">ff5bfc21-4336-4bc0-afc4-79c6af3316f7</thing-id>
        <type-id name="Blood pressure">ca3c57f4-f4c1-4e15-be67-0a3caf5414ed</type-id>
        <thing-state>Active</thing-state>
        <flags>0</flags>
        <eff-date>2016-09-01T18:08:56.34</eff-date>
        <created>
          <timestamp>2016-09-02T01:08:57.923Z</timestamp>
          <app-id name="Test Source">a94c245b-cd74-4fdf-bfaf-b6d8df05c27b</app-id>
          <person-id name="Test User">2d44d876-3bde-482b-a2af-ba133bc41fa9</person-id>
          <access-avenue>Offline</access-avenue>
          <audit-action>Created</audit-action>
          <master-app-id>5f2ece6b-6a74-4d39-8312-91d86df7e2db</master-app-id>
        </created>
        <updated>
          <timestamp>2016-09-02T01:08:57.923Z</timestamp>
          <app-id name="Test Source">a94c245b-cd74-4fdf-bfaf-b6d8df05c27b</app-id>
          <person-id name="Test User">2d44d876-3bde-482b-a2af-ba133bc41fa9</person-id>
          <access-avenue>Offline</access-avenue>
          <audit-action>Created</audit-action>
          <master-app-id>5f2ece6b-6a74-4d39-8312-91d86df7e2db</master-app-id>
        </updated>
        <data-xml>
          <blood-pressure>
            <when>
              <date>
                <y>2016</y>
                <m>9</m>
                <d>1</d>
              </date>
              <time>
                <h>18</h>
                <m>8</m>
                <s>56</s>
                <f>340</f>
              </time>
            </when>
            <systolic>120</systolic>
            <diastolic>80</diastolic>
            <pulse>64</pulse>
          </blood-pressure>
          <common />
        </data-xml>
        <eff-permissions immutable="false">
          <permission>Read</permission>
          <permission>Update</permission>
          <permission>Create</permission>
          <permission>Delete</permission>
        </eff-permissions>
      </thing>
    </group>
  </wc:info>
</response>